spotlite/__init__.py
spotlite/monitor.py
spotlite/search.py
spotlite/spotlite.py
spotlite/task.py
spotlite/tile.py
spotlite-0.10.0.dist-info/LICENSE
spotlite-0.10.0.dist-info/METADATA
spotlite-0.10.0.dist-info/WHEEL
spotlite-0.10.0.dist-info/top_level.txt
spotlite-0.10.0.dist-info/RECORD
