Metadata-Version: 2.1
Name: spotlite
Version: 0.10.0
Summary: Package to simplify working with Satellogic APIs
Home-page: https://github.com/mcarmich146/spotlite
Author: Mark
Author-email: your.email@example.com
Classifier: Development Status :: 3 - Alpha
Classifier: Intended Audience :: Developers
Classifier: License :: OSI Approved :: MIT License
Classifier: Programming Language :: Python :: 3
Classifier: Programming Language :: Python :: 3.11
Requires-Python: >=3.11.5
License-File: LICENSE
Requires-Dist: affine ==2.4.0
Requires-Dist: attrs ==23.1.0
Requires-Dist: branca ==0.6.0
Requires-Dist: cachetools ==5.3.2
Requires-Dist: certifi ==2023.7.22
Requires-Dist: charset-normalizer ==3.3.2
Requires-Dist: click ==8.1.7
Requires-Dist: click-plugins ==1.1.1
Requires-Dist: cligj ==0.7.2
Requires-Dist: contourpy ==1.1.1
Requires-Dist: cycler ==0.12.1
Requires-Dist: fiona ==1.9.5
Requires-Dist: folium ==0.14.0
Requires-Dist: fonttools ==4.43.1
Requires-Dist: geographiclib ==2.0
Requires-Dist: geojson ==3.0.1
Requires-Dist: geopandas ==0.14.0
Requires-Dist: geopy ==2.4.0
Requires-Dist: h11 ==0.14.0
Requires-Dist: httplib2 ==0.22.0
Requires-Dist: idna ==3.4
Requires-Dist: imageio ==2.33.1
Requires-Dist: jinja2 ==3.1.3
Requires-Dist: jsonschema ==4.19.2
Requires-Dist: jsonschema-specifications ==2023.7.1
Requires-Dist: kiwisolver ==1.4.5
Requires-Dist: MarkupSafe ==2.1.3
Requires-Dist: matplotlib ==3.8.1
Requires-Dist: numpy ==1.26.1
Requires-Dist: oauthlib ==3.2.2
Requires-Dist: outcome ==1.3.0.post0
Requires-Dist: packaging ==23.2
Requires-Dist: pandas ==2.1.2
Requires-Dist: pillow ==10.2.0
Requires-Dist: plotly ==5.18.0
Requires-Dist: protobuf ==4.25.0
Requires-Dist: pyasn1 ==0.5.0
Requires-Dist: pyasn1-modules ==0.3.0
Requires-Dist: pyparsing ==3.1.1
Requires-Dist: pyproj ==3.6.1
Requires-Dist: PySocks ==1.7.1
Requires-Dist: pystac ==1.9.0
Requires-Dist: pystac-client ==0.7.5
Requires-Dist: python-dateutil ==2.8.2
Requires-Dist: pytz ==2023.3.post1
Requires-Dist: rasterio ==1.3.9
Requires-Dist: referencing ==0.30.2
Requires-Dist: requests ==2.31.0
Requires-Dist: requests-oauthlib ==1.3.1
Requires-Dist: rpds-py ==0.10.6
Requires-Dist: rsa ==4.9
Requires-Dist: schedule ==1.2.1
Requires-Dist: selenium ==4.15.1
Requires-Dist: shapely ==2.0.2
Requires-Dist: six ==1.16.0
Requires-Dist: sniffio ==1.3.0
Requires-Dist: snuggs ==1.4.7
Requires-Dist: sortedcontainers ==2.4.0
Requires-Dist: tenacity ==8.2.3
Requires-Dist: trio ==0.22.2
Requires-Dist: trio-websocket ==0.11.1
Requires-Dist: tzdata ==2023.3
Requires-Dist: uritemplate ==4.1.1
Requires-Dist: urllib3 ==2.0.7
Requires-Dist: wsproto ==1.2.0
Requires-Dist: google-api-python-client >=2.114.0
Requires-Dist: google-auth-oauthlib >=1.2.0
